boi/__init__.py
boi/transcribe.py
owai/__init__.py
owai/transcribe.py
owai-0.1.0.dist-info/licenses/LICENSE
owai-0.1.0.dist-info/METADATA
owai-0.1.0.dist-info/WHEEL
owai-0.1.0.dist-info/top_level.txt
owai-0.1.0.dist-info/RECORD
