Metadata-Version: 2.4
Name: owai
Version: 0.1.0
Summary: An opinionated way of doing AI - Task-oriented ai nodes for general-computing
Author-email: SURUS AI <contact@surus.lat>
License: MIT
Project-URL: Homepage, https://surus.lat
Project-URL: Repository, https://github.com/surus-lat/owai
Project-URL: Documentation, https://docs.surus.lat
Keywords: ai,transcription,audio,whisper,canary,speech-to-text
Classifier: Development Status :: 4 - Beta
Classifier: Intended Audience :: Developers
Classifier: Programming Language :: Python :: 3
Classifier: Programming Language :: Python :: 3.8
Classifier: Programming Language :: Python :: 3.9
Classifier: Programming Language :: Python :: 3.10
Classifier: Programming Language :: Python :: 3.11
Classifier: Programming Language :: Python :: 3.12
Classifier: Topic :: Multimedia :: Sound/Audio :: Speech
Classifier: Topic :: Scientific/Engineering :: Artificial Intelligence
Requires-Python: >=3.8
License-File: LICENSE
Requires-Dist: requests>=2.25.0
Requires-Dist: python-dotenv>=1.0.0
Provides-Extra: dev
Requires-Dist: pytest>=7.0.0; extra == "dev"
Requires-Dist: black>=22.0.0; extra == "dev"
Requires-Dist: ruff>=0.1.0; extra == "dev"
Requires-Dist: twine>=6.1.0; extra == "dev"
Requires-Dist: pytest>=8.3.5; extra == "dev"
Dynamic: license-file
